orcakit_sdk/__init__.py
orcakit_sdk/context.py
orcakit_sdk/mcp_adapter.py
orcakit_sdk/model.py
orcakit_sdk/utils.py
orcakit_sdk/runner/__init__.py
orcakit_sdk/runner/agent.py
orcakit_sdk/runner/agent_executor.py
orcakit_sdk/runner/runner.py
orcakit_sdk/runner/channels/__init__.py
orcakit_sdk/runner/channels/a2a_channel.py
orcakit_sdk/runner/channels/base.py
orcakit_sdk/runner/channels/langgraph_channel.py
orcakit_sdk/runner/channels/mcp_server_channel.py
orcakit_sdk/runner/channels/openai_channel.py
orcakit_sdk/runner/channels/wework_channel.py
orcakit_sdk-0.1.13.dist-info/licenses/LICENSE
orcakit_sdk-0.1.13.dist-info/METADATA
orcakit_sdk-0.1.13.dist-info/WHEEL
orcakit_sdk-0.1.13.dist-info/top_level.txt
orcakit_sdk-0.1.13.dist-info/RECORD
