Metadata-Version: 2.4
Name: orcakit-sdk
Version: 0.1.13
Summary: OrcaKit SDK - Common utilities and adapters for AI Agent development based on LangGraph
Author-email: Jubao Liang <jubaoliang@gmail.com>
License-Expression: MIT
Requires-Python: <4.0,>=3.11
License-File: LICENSE
Requires-Dist: langgraph>=1.0.0
Requires-Dist: langchain>=1.0.0
Requires-Dist: langchain-core>=1.0.0
Requires-Dist: langchain-openai>=1.0.0
Requires-Dist: langchain-mcp-adapters>=0.1.9
Requires-Dist: langchain-tavily>=0.1
Requires-Dist: python-dotenv>=1.0.1
Requires-Dist: fastapi>=0.115.0
Requires-Dist: uvicorn>=0.32.0
Requires-Dist: langgraph-checkpoint-sqlite
Requires-Dist: langgraph-checkpoint-postgres
Requires-Dist: langfuse>=3.0.0
Requires-Dist: a2a-sdk>=0.3.15
Requires-Dist: scalar-fastapi>=1.0.0
Requires-Dist: pytest>=9.0.2
Provides-Extra: dev
Requires-Dist: mypy>=1.11.1; extra == "dev"
Requires-Dist: ruff>=0.6.1; extra == "dev"
Requires-Dist: pytest>=8.3.5; extra == "dev"
Requires-Dist: pytest-asyncio>=0.23.0; extra == "dev"
Requires-Dist: langchain-community>=0.3.0; extra == "dev"
Requires-Dist: tavily-python>=0.5.0; extra == "dev"
Requires-Dist: twine>=6.0.0; extra == "dev"
Dynamic: license-file
